{
    "title": "Tooltip",
    "tag": "ilw-tooltip",
    "github": "https://github.com/web-illinois/ilw-tooltip/",
    "type": "web component",
    "element-name": "ilw-tooltip",
    "description": "Ilw-tooltip is a popup that provides additional information about a user interface element, such as a button or link, when the mouse hovers over it.",
    "builder-version": "1.0-alpha",
    "version": "1.0.0-alpha",
    "date": "06/18/2025",
    "css": "https://dev.toolkit.illinois.edu/ilw-tooltip/1.0.0-alpha/ilw-tooltip.css",
    "js": "https://dev.toolkit.illinois.edu/ilw-tooltip/1.0.0-alpha/ilw-tooltip.js",
    "production": false,
    "notes": "",
    "parent-style": "margin: 20px 120px;",
    "samples": [
        {
            "name": "default",
            "description": "Default tooltip with a link trigger",
            "text": "<a href=\"javascript:void(0);\" slot=\"trigger\">Hover over me</a>\n        <div slot=\"content\">\n            This is a simple tooltip example.\n        </div>"
        },
        {
            "name": "Bold Text in tooltip",
            "description": "Tooltip with bold text",
            "text": "<button slot=\"trigger\" role=\"button\">\n <ilw-icon icon=\"home\" size=\"50px\" alt=\"Home\"></ilw-icon></button>\n <div slot=\"content\">\n Home\n </div>"
        },
        {
            "name": "Button Trigger",
            "description": "Button trigger with tooltip",
            "text": "<button slot=\"trigger\" role=\"button\" class=\"ilw-button\">\n Hover over me</button>\n <div slot=\"content\">This is additional information that appears when you hover over the button.</div>"
        }

    ],
    "attributes-fixed": [],
    "attributes-text": [],
    "attributes": [
        {
            "name": "theme",
            "description": "Color theme used",
            "depreciated": false,
            "values": [
                "",
                "blue"
            ]
        },
        {
            "name": "arrow",
            "description": "Position of the arrow and tooltip",
            "depreciated": false,
            "values": [
                "",
                "top-left",
                "top-center",
                "top-right",
                "left",
                "right",
                "bottom-left",
                "bottom-center",
                "bottom-right"
            ]
        }
    ],
    "classes-fixed": [],
    "classes": [],
    "css-variables": [
    ]
}
